Metadata-Version: 1.0
Name: cmstop
Version: 0.0.2
Summary: A set tools for cmstop (not release by offical).
Home-page: https://github.com/teachmyself/icmstop
Author: teachmyself
Author-email: teachmyself@126.com
License: MIT LICENSE
Keywords: cmstop,cms,top,cmstools
Platform: UNKNOWN
